sage_agent_internal/__init__.py
sage_agent_internal/_version.py
sage_agent_internal-0.5.14.data/data/share/jupyter/labextensions/sage-agent-internal/package.json
sage_agent_internal-0.5.14.data/data/share/jupyter/labextensions/sage-agent-internal/schemas/sage-agent-internal/package.json.orig
sage_agent_internal-0.5.14.data/data/share/jupyter/labextensions/sage-agent-internal/schemas/sage-agent-internal/plugin.json
sage_agent_internal-0.5.14.data/data/share/jupyter/labextensions/sage-agent-internal/static/122.ed16e34d871bf61b4bc4.js
sage_agent_internal-0.5.14.data/data/share/jupyter/labextensions/sage-agent-internal/static/220.f22bd3b6e323539a376e.js
sage_agent_internal-0.5.14.data/data/share/jupyter/labextensions/sage-agent-internal/static/262.b3a8cc7e7dfcf2f0be59.js
sage_agent_internal-0.5.14.data/data/share/jupyter/labextensions/sage-agent-internal/static/280.2bd19e5a931c15be1bfb.js
sage_agent_internal-0.5.14.data/data/share/jupyter/labextensions/sage-agent-internal/static/280.2bd19e5a931c15be1bfb.js.LICENSE.txt
sage_agent_internal-0.5.14.data/data/share/jupyter/labextensions/sage-agent-internal/static/353.b182eed12ec30f1a130b.js
sage_agent_internal-0.5.14.data/data/share/jupyter/labextensions/sage-agent-internal/static/363.8ce4c90c5227c39387ea.js
sage_agent_internal-0.5.14.data/data/share/jupyter/labextensions/sage-agent-internal/static/364.b7c5ccc06309d0278c1c.js
sage_agent_internal-0.5.14.data/data/share/jupyter/labextensions/sage-agent-internal/static/439.b11e85484b9c5deb58f9.js
sage_agent_internal-0.5.14.data/data/share/jupyter/labextensions/sage-agent-internal/static/481.ee20e115e7e6253b3c77.js
sage_agent_internal-0.5.14.data/data/share/jupyter/labextensions/sage-agent-internal/static/553.9fa43ddabefedad2cee0.js
sage_agent_internal-0.5.14.data/data/share/jupyter/labextensions/sage-agent-internal/static/553.9fa43ddabefedad2cee0.js.LICENSE.txt
sage_agent_internal-0.5.14.dist-info/METADATA
sage_agent_internal-0.5.14.dist-info/WHEEL
sage_agent_internal-0.5.14.dist-info/licenses/LICENSE
sage_agent_internal-0.5.14.dist-info/RECORD
